ttldict/__init__.py
ttldict/ttldict.py
ttldictionary-0.1.0.dist-info/LICENSE
ttldictionary-0.1.0.dist-info/METADATA
ttldictionary-0.1.0.dist-info/WHEEL
ttldictionary-0.1.0.dist-info/RECORD
