Metadata-Version: 2.1
Name: ttldictionary
Version: 0.1.0
Summary: Basic TTL system for Python dictionaries.
Home-page: https://github.com/notaussie/ttldict
License: MIT
Keywords: ttl
Author: NotAussie
Author-email: NotAussie@duck.com
Requires-Python: >=3.10,<4.0
Classifier: Development Status :: 3 - Alpha
Classifier: Intended Audience :: Developers
Classifier: License :: OSI Approved :: MIT License
Classifier: Programming Language :: Python :: 3
Classifier: Programming Language :: Python :: 3.10
Classifier: Programming Language :: Python :: 3.11
Classifier: Programming Language :: Python :: 3.12
Project-URL: Repository, https://github.com/notaussie/ttldict
